setup.py
krasi/__init__.py
krasi/helper.py
krasi.egg-info/PKG-INFO
krasi.egg-info/SOURCES.txt
krasi.egg-info/dependency_links.txt
krasi.egg-info/not-zip-safe
krasi.egg-info/top_level.txt