Metadata-Version: 1.0
Name: krasi
Version: 0.1
Summary: clinical trial information retriver
Home-page: https://github.com/gastrodia/krasi
Author: gastrodia
Author-email: ipv6.elata@gmail.com
License: MIT
Platform: UNKNOWN
